adafruit_24lc32.py
adafruit_circuitpython_24lc32-1.2.4.dist-info/licenses/LICENSE
adafruit_circuitpython_24lc32-1.2.4.dist-info/METADATA
adafruit_circuitpython_24lc32-1.2.4.dist-info/WHEEL
adafruit_circuitpython_24lc32-1.2.4.dist-info/top_level.txt
adafruit_circuitpython_24lc32-1.2.4.dist-info/RECORD
