Metadata-Version: 2.4
Name: adafruit-circuitpython-24lc32
Version: 1.2.4
Summary: CircuitPython driver for Adafruit 24LC32 I2C EEPROM Breakout
Author-email: Adafruit Industries <circuitpython@adafruit.com>
License: MIT
Project-URL: Homepage, https://github.com/adafruit/Adafruit_CircuitPython_24LC32.git
Keywords: adafruit,blinka,circuitpython,micropython,24lc32,EEPROM,memory,nvm
Classifier: Intended Audience :: Developers
Classifier: Topic :: Software Development :: Libraries
Classifier: Topic :: Software Development :: Embedded Systems
Classifier: Topic :: System :: Hardware
Classifier: License :: OSI Approved :: MIT License
Classifier: Programming Language :: Python :: 3
License-File: LICENSE
Requires-Dist: Adafruit-Blinka
Requires-Dist: adafruit-circuitpython-register
Requires-Dist: adafruit-circuitpython-busdevice
Provides-Extra: optional
Dynamic: license-file
